spark_calibration/__init__.py
spark_calibration/betacal.py
spark_calibration/metrics.py
spark_calibration/visualisation.py
spark_calibration-2.0.0.dist-info/METADATA
spark_calibration-2.0.0.dist-info/WHEEL
spark_calibration-2.0.0.dist-info/licenses/LICENSE
spark_calibration-2.0.0.dist-info/RECORD
