Metadata-Version: 2.4
Name: spark_calibration
Version: 2.0.0
Summary: Calibrating model scores/probabilities with PySpark DataFrames
Project-URL: Homepage, https://github.com/Meesho/spark_calibration
Project-URL: Bug Tracker, https://github.com/Meesho/spark_calibration/issues
Project-URL: Documentation, https://github.com/Meesho/spark_calibration#readme
Author-email: Jaya <jaya.kommuru@meesho.com>
License-Expression: Apache-2.0
License-File: LICENSE
Classifier: License :: OSI Approved :: Apache Software License
Classifier: Operating System :: OS Independent
Classifier: Programming Language :: Python :: 3
Requires-Python: >=3.7
Requires-Dist: numpy>=1.20.3
Requires-Dist: pandas>=1.3.0
Requires-Dist: plotly>=5.9.0
Requires-Dist: pyspark>=3.2.1
Requires-Dist: scikit-learn>=1.0.2
